<?xml version="1.0" encoding="utf-8"?>
<Config>
	<item Id="30001" GroupId="10001" Type="3" Weight="200" min="5" max="10" />
	<item Id="30002" GroupId="10001" Type="11311" Weight="10" min="1" max="1" />
	<item Id="30003" GroupId="10001" Type="11321" Weight="5" min="1" max="1" />
	<item Id="30004" GroupId="10001" Type="11331" Weight="3" min="1" max="1" />
	<item Id="30005" GroupId="10001" Type="11341" Weight="2" min="1" max="1" />
	<item Id="30006" GroupId="10001" Type="11351" Weight="10" min="1" max="1" />
	<item Id="30007" GroupId="10001" Type="11361" Weight="5" min="1" max="1" />
	<item Id="30008" GroupId="10001" Type="11371" Weight="3" min="1" max="1" />
	<item Id="30009" GroupId="10001" Type="11381" Weight="2" min="1" max="1" />
	<item Id="30010" GroupId="10001" Type="11391" Weight="100" min="1" max="1" />
	<item Id="30011" GroupId="10001" Type="11401" Weight="10" min="1" max="1" />
	<item Id="30012" GroupId="10001" Type="11411" Weight="3" min="1" max="1" />
	<item Id="30013" GroupId="10001" Type="201" Weight="40" min="1" max="1" />
	<item Id="30014" GroupId="10001" Type="202" Weight="10" min="1" max="1" />
	<item Id="30015" GroupId="10002" Type="3" Weight="200" min="10" max="20" />
	<item Id="30016" GroupId="10002" Type="11312" Weight="10" min="1" max="1" />
	<item Id="30017" GroupId="10002" Type="11322" Weight="5" min="1" max="1" />
	<item Id="30018" GroupId="10002" Type="11332" Weight="3" min="1" max="1" />
	<item Id="30019" GroupId="10002" Type="11342" Weight="2" min="1" max="1" />
	<item Id="30020" GroupId="10002" Type="11352" Weight="10" min="1" max="1" />
	<item Id="30021" GroupId="10002" Type="11362" Weight="5" min="1" max="1" />
	<item Id="30022" GroupId="10002" Type="11372" Weight="3" min="1" max="1" />
	<item Id="30023" GroupId="10002" Type="11382" Weight="2" min="1" max="1" />
	<item Id="30024" GroupId="10002" Type="11392" Weight="100" min="1" max="1" />
	<item Id="30025" GroupId="10002" Type="11402" Weight="10" min="1" max="1" />
	<item Id="30026" GroupId="10002" Type="11412" Weight="3" min="1" max="1" />
	<item Id="30027" GroupId="10002" Type="201" Weight="40" min="2" max="3" />
	<item Id="30028" GroupId="10002" Type="202" Weight="20" min="1" max="1" />
	<item Id="30029" GroupId="10003" Type="3" Weight="200" min="60" max="80" />
	<item Id="30030" GroupId="10003" Type="11313" Weight="10" min="1" max="1" />
	<item Id="30031" GroupId="10003" Type="11323" Weight="5" min="1" max="1" />
	<item Id="30032" GroupId="10003" Type="11333" Weight="3" min="1" max="1" />
	<item Id="30033" GroupId="10003" Type="11343" Weight="2" min="1" max="1" />
	<item Id="30034" GroupId="10003" Type="11353" Weight="10" min="1" max="1" />
	<item Id="30035" GroupId="10003" Type="11363" Weight="5" min="1" max="1" />
	<item Id="30036" GroupId="10003" Type="11373" Weight="3" min="1" max="1" />
	<item Id="30037" GroupId="10003" Type="11383" Weight="2" min="1" max="1" />
	<item Id="30038" GroupId="10003" Type="11393" Weight="100" min="1" max="1" />
	<item Id="30039" GroupId="10003" Type="11403" Weight="10" min="1" max="1" />
	<item Id="30040" GroupId="10003" Type="11413" Weight="3" min="1" max="1" />
	<item Id="30041" GroupId="10003" Type="201" Weight="40" min="4" max="6" />
	<item Id="30042" GroupId="10003" Type="202" Weight="20" min="1" max="1" />
	<item Id="30043" GroupId="10004" Type="10101" Weight="3000" min="1" max="1" />
	<item Id="30044" GroupId="10004" Type="10102" Weight="3000" min="1" max="1" />
	<item Id="30045" GroupId="10004" Type="10103" Weight="3000" min="1" max="1" />
	<item Id="30046" GroupId="10004" Type="10104" Weight="3000" min="1" max="1" />
	<item Id="30047" GroupId="10004" Type="10105" Weight="3000" min="1" max="1" />
	<item Id="30048" GroupId="10004" Type="10106" Weight="3000" min="1" max="1" />
	<item Id="30049" GroupId="10004" Type="10201" Weight="750" min="1" max="1" />
	<item Id="30050" GroupId="10004" Type="10202" Weight="750" min="1" max="1" />
	<item Id="30051" GroupId="10004" Type="10203" Weight="750" min="1" max="1" />
	<item Id="30052" GroupId="10004" Type="10204" Weight="750" min="1" max="1" />
	<item Id="30053" GroupId="10004" Type="10205" Weight="750" min="1" max="1" />
	<item Id="30054" GroupId="10004" Type="10206" Weight="750" min="1" max="1" />
	<item Id="30055" GroupId="10005" Type="10201" Weight="750" min="1" max="1" />
	<item Id="30056" GroupId="10005" Type="10202" Weight="750" min="1" max="1" />
	<item Id="30057" GroupId="10005" Type="10203" Weight="750" min="1" max="1" />
	<item Id="30058" GroupId="10005" Type="10204" Weight="750" min="1" max="1" />
	<item Id="30059" GroupId="10005" Type="10205" Weight="750" min="1" max="1" />
	<item Id="30060" GroupId="10005" Type="10206" Weight="750" min="1" max="1" />
	<item Id="30061" GroupId="10005" Type="10301" Weight="150" min="1" max="1" />
	<item Id="30062" GroupId="10005" Type="10302" Weight="150" min="1" max="1" />
	<item Id="30063" GroupId="10005" Type="10303" Weight="150" min="1" max="1" />
	<item Id="30064" GroupId="10005" Type="10304" Weight="150" min="1" max="1" />
	<item Id="30065" GroupId="10005" Type="10305" Weight="150" min="1" max="1" />
	<item Id="30066" GroupId="10005" Type="10306" Weight="150" min="1" max="1" />
	<item Id="30067" GroupId="10005" Type="10401" Weight="20" min="1" max="1" />
	<item Id="30068" GroupId="10005" Type="10402" Weight="15" min="1" max="1" />
	<item Id="30069" GroupId="10005" Type="10403" Weight="0" min="1" max="1" />
	<item Id="30070" GroupId="10005" Type="10404" Weight="12" min="1" max="1" />
	<item Id="30071" GroupId="10005" Type="10405" Weight="15" min="1" max="1" />
	<item Id="30072" GroupId="10005" Type="10406" Weight="20" min="1" max="1" />
	<item Id="30073" GroupId="10005" Type="10407" Weight="9" min="1" max="1" />
	<item Id="30074" GroupId="10005" Type="10408" Weight="9" min="1" max="1" />
	<item Id="30075" GroupId="10005" Type="10409" Weight="25" min="1" max="1" />
	<item Id="30076" GroupId="10005" Type="10410" Weight="25" min="1" max="1" />
	<item Id="30077" GroupId="10006" Type="10201" Weight="750" min="1" max="1" />
	<item Id="30078" GroupId="10006" Type="10202" Weight="750" min="1" max="1" />
	<item Id="30079" GroupId="10006" Type="10203" Weight="750" min="1" max="1" />
	<item Id="30080" GroupId="10006" Type="10204" Weight="750" min="1" max="1" />
	<item Id="30081" GroupId="10006" Type="10205" Weight="750" min="1" max="1" />
	<item Id="30082" GroupId="10006" Type="10206" Weight="750" min="1" max="1" />
	<item Id="30083" GroupId="10006" Type="10301" Weight="150" min="1" max="1" />
	<item Id="30084" GroupId="10006" Type="10302" Weight="150" min="1" max="1" />
	<item Id="30085" GroupId="10006" Type="10303" Weight="150" min="1" max="1" />
	<item Id="30086" GroupId="10006" Type="10304" Weight="150" min="1" max="1" />
	<item Id="30087" GroupId="10006" Type="10305" Weight="150" min="1" max="1" />
	<item Id="30088" GroupId="10006" Type="10306" Weight="150" min="1" max="1" />
	<item Id="30089" GroupId="10006" Type="10401" Weight="20" min="1" max="1" />
	<item Id="30090" GroupId="10006" Type="10402" Weight="15" min="1" max="1" />
	<item Id="30091" GroupId="10006" Type="10403" Weight="0" min="1" max="1" />
	<item Id="30092" GroupId="10006" Type="10404" Weight="12" min="1" max="1" />
	<item Id="30093" GroupId="10006" Type="10405" Weight="15" min="1" max="1" />
	<item Id="30094" GroupId="10006" Type="10406" Weight="20" min="1" max="1" />
	<item Id="30095" GroupId="10006" Type="10407" Weight="9" min="1" max="1" />
	<item Id="30096" GroupId="10006" Type="10408" Weight="9" min="1" max="1" />
	<item Id="30097" GroupId="10006" Type="10409" Weight="25" min="1" max="1" />
	<item Id="30098" GroupId="10006" Type="10410" Weight="25" min="1" max="1" />
	<item Id="30099" GroupId="10010" Type="10304" Weight="100" min="1" max="1" />
	<item Id="30100" GroupId="10011" Type="301" Weight="20" min="6" max="14" />
	<item Id="30101" GroupId="10011" Type="305" Weight="20" min="6" max="14" />
	<item Id="30102" GroupId="10012" Type="302" Weight="5" min="4" max="8" />
	<item Id="30103" GroupId="10012" Type="303" Weight="5" min="2" max="5" />
	<item Id="30104" GroupId="10013" Type="306" Weight="5" min="4" max="8" />
	<item Id="30105" GroupId="10013" Type="307" Weight="5" min="2" max="5" />
	<item Id="30106" GroupId="10021" Type="301" Weight="5" min="15" max="25" />
	<item Id="30107" GroupId="10021" Type="305" Weight="5" min="15" max="25" />
	<item Id="30108" GroupId="10022" Type="303" Weight="5" min="5" max="9" />
	<item Id="30109" GroupId="10022" Type="304" Weight="5" min="3" max="5" />
	<item Id="30110" GroupId="10023" Type="307" Weight="5" min="5" max="9" />
	<item Id="30111" GroupId="10023" Type="308" Weight="5" min="3" max="5" />
	<item Id="30112" GroupId="30101" Type="201" Weight="100" min="1" max="1" />
	<item Id="30113" GroupId="30102" Type="301" Weight="100" min="2" max="5" />
	<item Id="30114" GroupId="30103" Type="302" Weight="100" min="2" max="5" />
	<item Id="30115" GroupId="30104" Type="303" Weight="100" min="2" max="5" />
	<item Id="30116" GroupId="30105" Type="304" Weight="100" min="2" max="5" />
	<item Id="30117" GroupId="30106" Type="305" Weight="100" min="2" max="5" />
	<item Id="30118" GroupId="30107" Type="306" Weight="100" min="2" max="5" />
	<item Id="30119" GroupId="30108" Type="307" Weight="100" min="2" max="5" />
	<item Id="30120" GroupId="30109" Type="308" Weight="100" min="2" max="5" />
</Config>